{
  "version": "0.1",
  "source": "EXT_avatar_phonology@0.1",
  "handshapes": [
    {
      "code": "A",
      "description": "Poing fermé, pouce contre côté index",
      "angles": {"index.MCP": 75, "middle.MCP": 80, "ring.MCP": 78, "pinky.MCP": 75, "thumb.CMC": 30, "thumb.MCP": 20},
      "metadata": {"category": "fist", "frequencyRank": 2}
    },
    {
      "code": "B",
      "description": "Main plate doigts ensemble, pouce aligné",
      "angles": {"index.MCP": 5, "middle.MCP": 5, "ring.MCP": 5, "pinky.MCP": 7, "index.PIP": 0, "thumb.CMC": 5},
      "metadata": {"category": "flat", "frequencyRank": 1}
    },
    {
      "code": "5",
      "description": "Main ouverte doigts écartés naturels",
      "angles": {"index.MCP": 10, "middle.MCP": 12, "ring.MCP": 10, "pinky.MCP": 12, "splay.index": 8, "splay.pinky": 10},
      "metadata": {"category": "open", "frequencyRank": 3}
    },
    {
      "code": "C",
      "description": "Forme en C",
      "angles": {"index.MCP": 40, "middle.MCP": 45, "ring.MCP": 43, "pinky.MCP": 40, "index.PIP": 20, "thumb.CMC": 30, "thumb.MCP": 25},
      "metadata": {"category": "curved", "frequencyRank": 6}
    },
    {
      "code": "O",
      "description": "Extrémités doigts joignant pouce en cercle",
      "angles": {"index.MCP": 50, "middle.MCP": 52, "ring.MCP": 50, "pinky.MCP": 48, "index.PIP": 45, "thumb.CMC": 40, "thumb.MCP": 35},
      "metadata": {"category": "pinch-closed", "frequencyRank": 5}
    },
    {
      "code": "1",
      "description": "Index pointé, autres doigts fléchis",
      "angles": {"index.MCP": 5, "middle.MCP": 70, "ring.MCP": 70, "pinky.MCP": 68, "middle.PIP": 75, "thumb.CMC": 25},
      "metadata": {"category": "point", "frequencyRank": 4}
    },
    {
      "code": "L",
      "description": "Pouce et index en angle droit, autres fléchis",
      "angles": {"index.MCP": 5, "thumb.CMC": 35, "thumb.MCP": 15, "middle.MCP": 70, "ring.MCP": 70, "pinky.MCP": 70},
      "metadata": {"category": "classifier", "frequencyRank": 8}
    },
    {
      "code": "V",
      "description": "Index et majeur ouverts en V",
      "angles": {"index.MCP": 5, "middle.MCP": 5, "ring.MCP": 70, "pinky.MCP": 70, "middle.PIP": 0, "index.PIP": 0, "splay.index": 12},
      "metadata": {"category": "classifier", "frequencyRank": 7}
    },
    {
      "code": "3",
      "description": "Index, majeur, pouce étendus",
      "angles": {"index.MCP": 5, "middle.MCP": 5, "thumb.CMC": 25, "ring.MCP": 70, "pinky.MCP": 70},
      "metadata": {"category": "number", "frequencyRank": 9}
    },
    {
      "code": "4",
      "description": "Quatre doigts étendus sans pouce",
      "angles": {"index.MCP": 5, "middle.MCP": 5, "ring.MCP": 5, "pinky.MCP": 5, "thumb.CMC": 55},
      "metadata": {"category": "number", "frequencyRank": 10}
    },
    {
      "code": "I",
      "description": "Auriculaire étendu, autres fléchis",
      "angles": {"pinky.MCP": 5, "index.MCP": 70, "middle.MCP": 70, "ring.MCP": 70, "thumb.CMC": 25},
      "metadata": {"category": "letter", "frequencyRank": 12}
    },
    {
      "code": "Y",
      "description": "Pouce et auriculaire étendus",
      "angles": {"pinky.MCP": 5, "thumb.CMC": 35, "index.MCP": 70, "middle.MCP": 70, "ring.MCP": 70},
      "metadata": {"category": "letter", "frequencyRank": 13}
    },
    {
      "code": "F",
      "description": "Pouce et index en cercle, autres étendus",
      "angles": {"index.MCP": 45, "index.PIP": 40, "thumb.CMC": 45, "thumb.MCP": 35, "middle.MCP": 5, "ring.MCP": 5, "pinky.MCP": 5},
      "metadata": {"category": "pinch", "frequencyRank": 11}
    },
    {
      "code": "Relaxed-5",
      "description": "Main ouverte détendue",
      "angles": {"index.MCP": 15, "middle.MCP": 18, "ring.MCP": 17, "pinky.MCP": 20, "thumb.CMC": 20},
      "metadata": {"category": "open", "frequencyRank": 14}
    },
    {
      "code": "Flat-O",
      "description": "Doigts courbés plats vers pouce (forme O aplatie)",
      "angles": {"index.MCP": 45, "index.PIP": 35, "thumb.CMC": 40, "middle.MCP": 47, "ring.MCP": 45, "pinky.MCP": 42},
      "metadata": {"category": "pinch-flat", "frequencyRank": 15}
    }
  ]
}
